{"894034804503351366":{"commandsRun":13,"firstCommand":"1689890965","lastUpdated":"1695608897","commands":{"guild":5,"fun-facts":1,"about":1,"user":1,"stats":5}},"501976955998961664":{"commandsRun":3,"firstCommand":"1690189233","lastUpdated":"1690189405","commands":{"fun-facts":3}},"964967961263767652":{"commandsRun":2,"firstCommand":"1690284549","lastUpdated":"1690285115","commands":{"fun-facts":2}},"933349617054126110":{"commandsRun":6,"firstCommand":"1690604796","lastUpdated":"1690607342","commands":{"fun-facts":5,"fun-facts-dev":1}},"619208257721860108":{"commandsRun":7,"firstCommand":"1691199840","lastUpdated":"1695897302","commands":{"report-bug":1,"about":2,"stats":2,"quests":2}},"468043261911498767":{"commandsRun":15,"firstCommand":"1694910944","lastUpdated":"1695081467","commands":{"about":1,"guild":1,"stats":3,"report-bug":10}},"728254498018951238":{"commandsRun":1,"firstCommand":"1695294348","lastUpdated":"1695294348","commands":{"stats":1}},"1077740824416239767":{"commandsRun":4,"firstCommand":"1696260309","lastUpdated":"1696260518","commands":{"stats":3,"report-bug":1}},"608584543506530314":{"commandsRun":2,"firstCommand":"1696393141","lastUpdated":"1696393204","commands":{"stats":2}}}
